akasia.py
Akasia-1.7.1.dist-info/AUTHORS.md
Akasia-1.7.1.dist-info/LICENSE
Akasia-1.7.1.dist-info/METADATA
Akasia-1.7.1.dist-info/WHEEL
Akasia-1.7.1.dist-info/entry_points.txt
Akasia-1.7.1.dist-info/top_level.txt
Akasia-1.7.1.dist-info/RECORD
