Metadata-Version: 2.1
Name: Akasia
Version: 1.7.1
Summary: A fork tiny python text-based web browser Asiakas.
Home-page: UNKNOWN
Author: Robrecht De Rouck
Author-email: Robrecht.De.Rouck@gmail.com
Maintainer: RIDERIUS
Maintainer-email: riderius.help@gmail.com
License: MIT License
Project-URL: Source Code, https://github.com/RIDERIUS/Akasia
Platform: UNKNOWN
Classifier: License :: OSI Approved :: MIT License
Classifier: Programming Language :: Python :: 3.9
Classifier: Programming Language :: Python :: 3.8
Classifier: Programming Language :: Python :: 3.7
Classifier: Programming Language :: Python :: 3.6
Classifier: Programming Language :: Python :: 3 :: Only
Classifier: Programming Language :: Python :: Implementation :: CPython
Classifier: Environment :: Console
Classifier: Topic :: Internet :: WWW/HTTP :: Browsers
Requires-Python: >=3.6
Requires-Dist: dock-python (>=0.1.0)
Requires-Dist: html2text (>=2020.1.16)
Requires-Dist: requests (>=2.25.1)
Requires-Dist: rich (>=9.12.4)
Requires-Dist: wikipedia (>=1.4.0)
